setup.py
erl_terms/__init__.py
erl_terms/erl_terms_core.py
erl_terms.egg-info/PKG-INFO
erl_terms.egg-info/SOURCES.txt
erl_terms.egg-info/dependency_links.txt
erl_terms.egg-info/requires.txt
erl_terms.egg-info/top_level.txt